Metadata-Version: 2.0
Name: graphite-beacon
Version: 0.27.0
Summary: Simple alerting system for Graphite metrics.
Requires-Dist: tornado (==4.4.2)
Requires-Dist: funcparserlib (==0.3.6)
Requires-Dist: pyyaml (==3.12)
